cqi_python/CQI.py
cqi_cpp/src/wrapper/qtree_wrapper.cpython-37m-x86_64-linux-gnu.so
cqi_rl-1.1.0.dist-info/LICENSE
cqi_rl-1.1.0.dist-info/top_level.txt
cqi_rl-1.1.0.dist-info/RECORD
cqi_rl-1.1.0.dist-info/METADATA
cqi_rl-1.1.0.dist-info/WHEEL
