Metadata-Version: 2.1
Name: cqi-rl
Version: 1.1.0
Summary: A C++ implementation of Conservative Q-Improvement
Home-page: https://github.com/AMR-/Conservative-Q-Improvement
Author: Aaron M. Roth, Nicholay Topin, Saadiq K. Shaik
Author-email: amroth@umd.edu
License: MIT
Platform: UNKNOWN
Classifier: License :: OSI Approved :: MIT License
Classifier: Programming Language :: Python :: 3
Classifier: Programming Language :: Python :: 3.7
Classifier: Development Status :: 3 - Alpha
Classifier: Intended Audience :: Developers
Classifier: Intended Audience :: Science/Research
Classifier: Topic :: Scientific/Engineering
Classifier: Topic :: Scientific/Engineering :: Artificial Intelligence
Classifier: Topic :: Software Development :: Libraries :: Python Modules
Requires-Dist: cython
Requires-Dist: ray
